kittycat/MANIFEST.in
kittycat/__init__.py
kittycat/__pycache__/__init__.cpython-37.pyc
kittycat/static/.DS_Store
kittycat/static/catherder/.DS_Store
kittycat/static/catherder/3rdpartylicenses.txt
kittycat/static/catherder/Poppins-Bold.3588653249d857a419d7.woff2
kittycat/static/catherder/Poppins-Bold.7940efc40d8e3b477e16.ttf
kittycat/static/catherder/Poppins-Bold.81873d33ae530a7a1bee.woff
kittycat/static/catherder/Poppins-Light.3352653dedd571bbc490.ttf
kittycat/static/catherder/Poppins-Light.3a7edf2f61eba7ba6b4d.woff2
kittycat/static/catherder/Poppins-Light.ceaf8c4de9ee0f8530fd.woff
kittycat/static/catherder/Poppins-Regular.1ed9a698de5b1b3328ff.woff
kittycat/static/catherder/Poppins-Regular.731a28a413d642522667.ttf
kittycat/static/catherder/Poppins-Regular.e02e190248839fec5932.woff2
kittycat/static/catherder/favicon.ico
kittycat/static/catherder/index.html
kittycat/static/catherder/main.f469d0a4979dc4434e03.js
kittycat/static/catherder/polyfills.2f4a59095805af02bd79.js
kittycat/static/catherder/runtime.a66f828dca56eeb90e02.js
kittycat/static/catherder/styles.8365474530bb121e9e71.css
kittycat/static/catherder/assets/logo.svg
kittycat/static/catherder/assets/fonts/Poppins/OFL.txt
kittycat/static/catherder/assets/fonts/Poppins/Poppins-Black.ttf
kittycat/static/catherder/assets/fonts/Poppins/Poppins-Black.woff
kittycat/static/catherder/assets/fonts/Poppins/Poppins-Black.woff2
kittycat/static/catherder/assets/fonts/Poppins/Poppins-BlackItalic.ttf
kittycat/static/catherder/assets/fonts/Poppins/Poppins-BlackItalic.woff
kittycat/static/catherder/assets/fonts/Poppins/Poppins-BlackItalic.woff2
kittycat/static/catherder/assets/fonts/Poppins/Poppins-Bold.ttf
kittycat/static/catherder/assets/fonts/Poppins/Poppins-Bold.woff
kittycat/static/catherder/assets/fonts/Poppins/Poppins-Bold.woff2
kittycat/static/catherder/assets/fonts/Poppins/Poppins-BoldItalic.ttf
kittycat/static/catherder/assets/fonts/Poppins/Poppins-BoldItalic.woff
kittycat-1.0.1.dist-info/METADATA
kittycat-1.0.1.dist-info/WHEEL
kittycat-1.0.1.dist-info/entry_points.txt
kittycat-1.0.1.dist-info/top_level.txt
kittycat-1.0.1.dist-info/zip-safe
kittycat-1.0.1.dist-info/RECORD
