Metadata-Version: 2.1
Name: kittycat
Version: 1.0.1
Summary: asyncio REST API Resource database
Home-page: https://github.com/plone/kittycat
Author: David Glick
Author-email: david@glicksoftware.com
License: BSD
Keywords: asyncio,REST,Framework,transactional
Platform: UNKNOWN
Classifier: License :: OSI Approved :: BSD License
Classifier: Intended Audience :: Developers
Classifier: Topic :: Internet :: WWW/HTTP
Classifier: Programming Language :: Python :: 3.6
Classifier: Programming Language :: Python :: 3.7
Classifier: Topic :: Software Development :: Libraries :: Python Modules
Requires-Dist: guillotina
